PluginSDK.py
PluginSDK-0.1.0.dist-info/METADATA
PluginSDK-0.1.0.dist-info/WHEEL
PluginSDK-0.1.0.dist-info/top_level.txt
PluginSDK-0.1.0.dist-info/RECORD
